ShiyongSpringCloudYuDockerShizhanWeiFuwu/README.md
ShiyongSpringCloudYuDockerShizhanWeiFuwu/__init__.py
ShiyongSpringCloudYuDockerShizhanWeiFuwu/__main__.py
ShiyongSpringCloudYuDockerShizhanWeiFuwu/file.epub
ShiyongSpringCloudYuDockerShizhanWeiFuwu/index.html
ShiyongSpringCloudYuDockerShizhanWeiFuwu/css/__init__.py
ShiyongSpringCloudYuDockerShizhanWeiFuwu/css/annotations.css
ShiyongSpringCloudYuDockerShizhanWeiFuwu/css/main.css
ShiyongSpringCloudYuDockerShizhanWeiFuwu/css/normalize.css
ShiyongSpringCloudYuDockerShizhanWeiFuwu/css/popup.css
ShiyongSpringCloudYuDockerShizhanWeiFuwu/font/__init__.py
ShiyongSpringCloudYuDockerShizhanWeiFuwu/font/fontello.eot
ShiyongSpringCloudYuDockerShizhanWeiFuwu/font/fontello.svg
ShiyongSpringCloudYuDockerShizhanWeiFuwu/font/fontello.ttf
ShiyongSpringCloudYuDockerShizhanWeiFuwu/font/fontello.woff
ShiyongSpringCloudYuDockerShizhanWeiFuwu/img/__init__.py
ShiyongSpringCloudYuDockerShizhanWeiFuwu/img/annotator-glyph-sprite.png
ShiyongSpringCloudYuDockerShizhanWeiFuwu/img/annotator-icon-sprite.png
ShiyongSpringCloudYuDockerShizhanWeiFuwu/img/apple-touch-icon.png
ShiyongSpringCloudYuDockerShizhanWeiFuwu/img/cancelfullscreen.png
ShiyongSpringCloudYuDockerShizhanWeiFuwu/img/close.png
ShiyongSpringCloudYuDockerShizhanWeiFuwu/img/fullscreen.png
ShiyongSpringCloudYuDockerShizhanWeiFuwu/img/loader.gif
ShiyongSpringCloudYuDockerShizhanWeiFuwu/img/menu-icon.png
ShiyongSpringCloudYuDockerShizhanWeiFuwu/img/save.png
ShiyongSpringCloudYuDockerShizhanWeiFuwu/img/saved.png
ShiyongSpringCloudYuDockerShizhanWeiFuwu/img/settings-s.png
ShiyongSpringCloudYuDockerShizhanWeiFuwu/img/settings.png
ShiyongSpringCloudYuDockerShizhanWeiFuwu/img/star.png
ShiyongSpringCloudYuDockerShizhanWeiFuwu/js/__init__.py
ShiyongSpringCloudYuDockerShizhanWeiFuwu/js/epub.js
ShiyongSpringCloudYuDockerShizhanWeiFuwu/js/epub.min.js
ShiyongSpringCloudYuDockerShizhanWeiFuwu/js/epub.min.map
ShiyongSpringCloudYuDockerShizhanWeiFuwu/js/hooks.min.js
shiyong_spring_cloud_yu_docker_shizhan_wei_fuwu-2024.3.3.0.dist-info/METADATA
shiyong_spring_cloud_yu_docker_shizhan_wei_fuwu-2024.3.3.0.dist-info/WHEEL
shiyong_spring_cloud_yu_docker_shizhan_wei_fuwu-2024.3.3.0.dist-info/entry_points.txt
shiyong_spring_cloud_yu_docker_shizhan_wei_fuwu-2024.3.3.0.dist-info/top_level.txt
shiyong_spring_cloud_yu_docker_shizhan_wei_fuwu-2024.3.3.0.dist-info/RECORD
